defillama/__init__.py
defillama/__version__.py
defillama/defillama.py
DeFiLlama-2.3.0.dist-info/LICENSE
DeFiLlama-2.3.0.dist-info/METADATA
DeFiLlama-2.3.0.dist-info/WHEEL
DeFiLlama-2.3.0.dist-info/top_level.txt
DeFiLlama-2.3.0.dist-info/RECORD
